crfs-0.2.0.dist-info/METADATA
crfs-0.2.0.dist-info/WHEEL
crfs.libs/libgcc_s-08f7558e.so.1
crfs/__init__.py
crfs/__init__.pyi
crfs/py.typed
crfs/crfs.abi3.so
crfs-0.2.0.dist-info/RECORD
