Metadata-Version: 2.1
Name: crfs
Version: 0.2.0
Keywords: crf,crfsuite
Home-Page: https://github.com/messense/crfs-rs
Author: messense <messense@icloud.com>
Author-email: messense <messense@icloud.com>
License: MIT
Project-URL: Source Code, https://github.com/messense/crfs-rs.git
